sm_data_ml_utils/core/__init__.py
sm_data_ml_utils/core/config.py
sm_data_ml_utils/core/databricks_utils.py
sm_data_ml_utils/databricks_client/__init__.py
sm_data_ml_utils/databricks_client/client.py
sm_data_ml_utils/databricks_client/databricks-sql.ipynb
sm_data_ml_utils/mlflow_databricks/__init__.py
sm_data_ml_utils/mlflow_databricks/mlflow_model_utils.py
sm_data_ml_utils/mlflow_databricks/mlflow_prediction_requests.py
sm_data_ml_utils/mlflow_databricks/mlflow_serve.py
sm_data_ml_utils/mlflow_databricks/mlflow_tracker.py
sm_data_ml_utils-0.1.3.dist-info/LICENSE.txt
sm_data_ml_utils-0.1.3.dist-info/METADATA
sm_data_ml_utils-0.1.3.dist-info/WHEEL
sm_data_ml_utils-0.1.3.dist-info/RECORD
